ezdxf_shapely/__init__.py
ezdxf_shapely/conversion.py
ezdxf_shapely/sanitization.py
ezdxf_shapely/utils.py
ezdxf_shapely-1.0.dist-info/METADATA
ezdxf_shapely-1.0.dist-info/WHEEL
ezdxf_shapely-1.0.dist-info/licenses/LICENSE
ezdxf_shapely-1.0.dist-info/RECORD
