Metadata-Version: 2.3
Name: ezdxf-shapely
Version: 1.0
Summary: Convert DXF entities created by ezdxf to shapely geomerty objects.
Project-URL: Homepage, https://github.com/axtimhaus/ezdxf-shapely
Project-URL: Repository, https://github.com/axtimhaus/ezdxf-shapely
Project-URL: ForkedFrom, https://github.com/aegis1980/cad-to-shapely
Author-email: Max Weiner <max.weiner@posteo.de>, Jon Robinson <jonrobinson1980@gmail.com>
Maintainer-email: Max Weiner <max.weiner@posteo.de>
Classifier: Development Status :: 4 - Beta
Classifier: Intended Audience :: Science/Research
Classifier: License :: OSI Approved :: MIT License
Classifier: Programming Language :: Python :: 3 :: Only
Classifier: Topic :: Scientific/Engineering
Requires-Python: >=3.10
Requires-Dist: ezdxf~=1.3
Requires-Dist: geomdl~=5.3
Requires-Dist: numpy~=2.0
Requires-Dist: shapely<3.0,>=2.0.6
